{
    "os": "Linux-4.4.0-59-generic-x86_64-with-debian-buster-sid",
    "python": "3.7.7",
    "heartbeatAt": "2021-04-19T03:13:35.746367",
    "startedAt": "2021-04-19T03:13:33.098577",
    "docker": null,
    "gpu": "Tesla V100-PCIE-32GB",
    "gpu_count": 1,
    "cpu_count": 16,
    "cuda": null,
    "args": [],
    "state": "running",
    "program": "train.py",
    "codePath": "train.py",
    "git": {
        "remote": "https://github.com/iloveslowfood/RelationExtraction.git",
        "commit": "4dae1ff56eca4862970e9d22fa36cb6409a1e0e2"
    },
    "email": "silkstaff@naver.com",
    "root": "/opt/ml/RelationExtraction",
    "host": "f5834a502924",
    "username": "root",
    "executable": "/opt/conda/bin/python"
}
